upt_pypi/__init__.py
upt_pypi/licenses.py
upt_pypi/upt_pypi.py
upt_pypi/tests/__init__.py
upt_pypi/tests/test_licenses.py
upt_pypi/tests/test_upt_pypi.py
upt_pypi-0.6.dist-info/LICENSE
upt_pypi-0.6.dist-info/METADATA
upt_pypi-0.6.dist-info/WHEEL
upt_pypi-0.6.dist-info/entry_points.txt
upt_pypi-0.6.dist-info/top_level.txt
upt_pypi-0.6.dist-info/RECORD
